logtrail/__init__.py
logtrail/colors.py
logtrail/compatible.py
logtrail/logger.py
logtrail/symbols.py
logtrail-0.0.3.dist-info/DESCRIPTION.rst
logtrail-0.0.3.dist-info/METADATA
logtrail-0.0.3.dist-info/RECORD
logtrail-0.0.3.dist-info/WHEEL
logtrail-0.0.3.dist-info/metadata.json
logtrail-0.0.3.dist-info/top_level.txt
logtrail-0.0.3.dist-info/zip-safe
